{
  "packets":{
    "actorList":["0-1427","0-1428","0-1429","0-1430","0-1431","0-1432","414348-0","56068-0"],
    "ai":[],
    "cellChangeFrom":[],
    "cellChangeTo":[],
    "container":["55946-0","55947-0","55948-0","55950-0","55951-0","55953-0","56018-0","56019-0","56020-0","56022-0","56023-0","56025-0","56026-0","56028-0","56031-0","56032-0","56033-0","56034-0","56035-0","56078-0","56083-0","56085-0","56086-0","56089-0","56090-0","56091-0","56094-0","56095-0","56096-0","56102-0","56104-0","56105-0","56106-0","56107-0","56108-0","56137-0","56138-0","56139-0","56140-0","56141-0","414348-0","56068-0"],
    "death":[],
    "delete":[],
    "doorState":[],
    "equipment":["414348-0"],
    "lock":[],
    "place":[],
    "position":["414348-0","56068-0","0-1427","0-1428","0-1429","0-1430","0-1431","0-1432"],
    "scale":[],
    "spawn":["0-1427","0-1428","0-1429","0-1430","0-1431","0-1432"],
    "state":[],
    "statsDynamic":["414348-0","56068-0","0-1427","0-1428","0-1429","0-1430","0-1431","0-1432"],
    "trap":[]
  },
  "entry":{
    "creationTime":1547248125,
    "description":"Madas-Zebba Egg Mine"
  },
  "lastVisit":{
    "urm":1547248125
  },
  "recordLinks":[],
  "objectData":{
    "55951-0":{
      "refId":"egg_kwama00",
      "inventory":[{
          "refId":"food_kwama_egg_02",
          "count":1,
          "charge":-1,
          "enchantmentCharge":-1,
          "soul":""
        }]
    },
    "56091-0":{
      "refId":"egg_kwama00",
      "inventory":[{
          "refId":"food_kwama_egg_02",
          "count":1,
          "charge":-1,
          "enchantmentCharge":-1,
          "soul":""
        }]
    },
    "55948-0":{
      "refId":"egg_kwama00",
      "inventory":[{
          "refId":"food_kwama_egg_02",
          "count":1,
          "charge":-1,
          "enchantmentCharge":-1,
          "soul":""
        }]
    },
    "56078-0":{
      "refId":"egg_kwama00",
      "inventory":[{
          "refId":"food_kwama_egg_02",
          "count":1,
          "charge":-1,
          "enchantmentCharge":-1,
          "soul":""
        }]
    },
    "56137-0":{
      "refId":"egg_kwama00",
      "inventory":[{
          "refId":"food_kwama_egg_02",
          "count":1,
          "charge":-1,
          "enchantmentCharge":-1,
          "soul":""
        }]
    },
    "56085-0":{
      "refId":"egg_kwama00",
      "inventory":[{
          "refId":"food_kwama_egg_02",
          "count":1,
          "charge":-1,
          "enchantmentCharge":-1,
          "soul":""
        }]
    },
    "56138-0":{
      "refId":"egg_kwama00",
      "inventory":[{
          "refId":"food_kwama_egg_02",
          "count":1,
          "charge":-1,
          "enchantmentCharge":-1,
          "soul":""
        }]
    },
    "56032-0":{
      "refId":"egg_kwama00",
      "inventory":[{
          "refId":"food_kwama_egg_02",
          "count":1,
          "charge":-1,
          "enchantmentCharge":-1,
          "soul":""
        }]
    },
    "0-1429":{
      "refId":"scrib diseased",
      "location":{
        "posX":1464.3286132813,
        "posZ":-887.50085449219,
        "posY":6683.2456054688,
        "rotX":0,
        "rotY":0,
        "rotZ":0
      },
      "stats":{
        "healthCurrent":8,
        "magickaCurrent":12,
        "healthModified":8,
        "fatigueBase":74,
        "fatigueModified":74,
        "healthBase":8,
        "magickaModified":12,
        "magickaBase":12,
        "fatigueCurrent":74
      }
    },
    "0-1432":{
      "refId":"kwama worker blighted",
      "location":{
        "posX":2683.6845703125,
        "posZ":-1092.8597412109,
        "posY":4797.0805664063,
        "rotX":0,
        "rotY":0,
        "rotZ":0
      },
      "stats":{
        "healthCurrent":60,
        "magickaCurrent":8,
        "healthModified":60,
        "fatigueBase":400,
        "fatigueModified":400,
        "healthBase":60,
        "magickaModified":8,
        "magickaBase":8,
        "fatigueCurrent":400
      }
    },
    "56035-0":{
      "refId":"egg_kwama00",
      "inventory":[{
          "refId":"food_kwama_egg_02",
          "count":1,
          "charge":-1,
          "enchantmentCharge":-1,
          "soul":""
        }]
    },
    "56090-0":{
      "refId":"egg_kwama00",
      "inventory":[{
          "refId":"food_kwama_egg_02",
          "count":1,
          "charge":-1,
          "enchantmentCharge":-1,
          "soul":""
        }]
    },
    "56020-0":{
      "refId":"egg_kwama00",
      "inventory":[{
          "refId":"food_kwama_egg_02",
          "count":1,
          "charge":-1,
          "enchantmentCharge":-1,
          "soul":""
        }]
    },
    "0-1428":{
      "refId":"kwama worker blighted",
      "location":{
        "posX":2444.7436523438,
        "posZ":-888.55615234375,
        "posY":7007.46484375,
        "rotX":0,
        "rotY":0,
        "rotZ":0
      },
      "stats":{
        "healthCurrent":60,
        "magickaCurrent":8,
        "healthModified":60,
        "fatigueBase":400,
        "fatigueModified":400,
        "healthBase":60,
        "magickaModified":8,
        "magickaBase":8,
        "fatigueCurrent":400
      }
    },
    "56102-0":{
      "refId":"egg_kwama00",
      "inventory":[{
          "refId":"food_kwama_egg_02",
          "count":1,
          "charge":-1,
          "enchantmentCharge":-1,
          "soul":""
        }]
    },
    "56140-0":{
      "refId":"egg_kwama00",
      "inventory":[{
          "refId":"food_kwama_egg_02",
          "count":1,
          "charge":-1,
          "enchantmentCharge":-1,
          "soul":""
        }]
    },
    "56089-0":{
      "refId":"egg_kwama00",
      "inventory":[{
          "refId":"food_kwama_egg_02",
          "count":1,
          "charge":-1,
          "enchantmentCharge":-1,
          "soul":""
        }]
    },
    "55947-0":{
      "refId":"egg_kwama00",
      "inventory":[{
          "refId":"food_kwama_egg_02",
          "count":1,
          "charge":-1,
          "enchantmentCharge":-1,
          "soul":""
        }]
    },
    "56096-0":{
      "refId":"egg_kwama00",
      "inventory":[{
          "refId":"food_kwama_egg_02",
          "count":1,
          "charge":-1,
          "enchantmentCharge":-1,
          "soul":""
        }]
    },
    "0-1427":{
      "refId":"kwama worker blighted",
      "location":{
        "posX":1464.2751464844,
        "posZ":-877.51226806641,
        "posY":7429.115234375,
        "rotX":0,
        "rotY":0,
        "rotZ":0
      },
      "stats":{
        "healthCurrent":60,
        "magickaCurrent":8,
        "healthModified":60,
        "fatigueBase":400,
        "fatigueModified":400,
        "healthBase":60,
        "magickaModified":8,
        "magickaBase":8,
        "fatigueCurrent":400
      }
    },
    "55946-0":{
      "refId":"egg_kwama00",
      "inventory":[{
          "refId":"food_kwama_egg_02",
          "count":1,
          "charge":-1,
          "enchantmentCharge":-1,
          "soul":""
        }]
    },
    "56033-0":{
      "refId":"egg_kwama00",
      "inventory":[{
          "refId":"food_kwama_egg_02",
          "count":1,
          "charge":-1,
          "enchantmentCharge":-1,
          "soul":""
        }]
    },
    "56028-0":{
      "refId":"egg_kwama00",
      "inventory":[{
          "refId":"food_kwama_egg_02",
          "count":1,
          "charge":-1,
          "enchantmentCharge":-1,
          "soul":""
        }]
    },
    "56018-0":{
      "refId":"egg_kwama00",
      "inventory":[{
          "refId":"food_kwama_egg_02",
          "count":1,
          "charge":-1,
          "enchantmentCharge":-1,
          "soul":""
        }]
    },
    "0-1430":{
      "refId":"kwama worker blighted",
      "location":{
        "posX":3384.0512695313,
        "posZ":-1017.8494873047,
        "posY":6706.9873046875,
        "rotX":0,
        "rotY":0,
        "rotZ":0
      },
      "stats":{
        "healthCurrent":60,
        "magickaCurrent":8,
        "healthModified":60,
        "fatigueBase":400,
        "fatigueModified":400,
        "healthBase":60,
        "magickaModified":8,
        "magickaBase":8,
        "fatigueCurrent":400
      }
    },
    "56104-0":{
      "refId":"egg_kwama00",
      "inventory":[{
          "refId":"food_kwama_egg_02",
          "count":1,
          "charge":-1,
          "enchantmentCharge":-1,
          "soul":""
        }]
    },
    "0-1431":{
      "refId":"kwama worker blighted",
      "location":{
        "posX":4417.998046875,
        "posZ":-1144.8913574219,
        "posY":4400.216796875,
        "rotX":0,
        "rotY":0,
        "rotZ":0
      },
      "stats":{
        "healthCurrent":60,
        "magickaCurrent":8,
        "healthModified":60,
        "fatigueBase":400,
        "fatigueModified":400,
        "healthBase":60,
        "magickaModified":8,
        "magickaBase":8,
        "fatigueCurrent":400
      }
    },
    "56068-0":{
      "refId":"kwama queen_madas",
      "location":{
        "posX":3803.623046875,
        "posZ":-1133.5194091797,
        "posY":4936.2172851563,
        "rotX":0,
        "rotY":0,
        "rotZ":5.895574092865
      },
      "stats":{
        "healthCurrent":50,
        "magickaCurrent":50,
        "healthModified":50,
        "fatigueBase":50,
        "fatigueModified":50,
        "healthBase":50,
        "magickaModified":50,
        "magickaBase":50,
        "fatigueCurrent":50
      },
      "inventory":[{
          "refId":"ingred_kwama_cuttle_01",
          "count":1,
          "charge":-1,
          "enchantmentCharge":-1,
          "soul":""
        },{
          "refId":"food_kwama_egg_01",
          "count":2,
          "charge":-1,
          "enchantmentCharge":-1,
          "soul":""
        }]
    },
    "56139-0":{
      "refId":"egg_kwama00",
      "inventory":[{
          "refId":"food_kwama_egg_02",
          "count":1,
          "charge":-1,
          "enchantmentCharge":-1,
          "soul":""
        }]
    },
    "56141-0":{
      "refId":"egg_kwama00",
      "inventory":[{
          "refId":"food_kwama_egg_02",
          "count":1,
          "charge":-1,
          "enchantmentCharge":-1,
          "soul":""
        }]
    },
    "56025-0":{
      "refId":"egg_kwama00",
      "inventory":[{
          "refId":"food_kwama_egg_02",
          "count":1,
          "charge":-1,
          "enchantmentCharge":-1,
          "soul":""
        }]
    },
    "414348-0":{
      "refId":"dead random male",
      "location":{
        "posX":3519.478515625,
        "posZ":-1152.5998535156,
        "posY":5902.58203125,
        "rotX":0,
        "rotY":0,
        "rotZ":0
      },
      "stats":{
        "healthCurrent":0,
        "magickaCurrent":92,
        "healthModified":0,
        "fatigueBase":216,
        "fatigueModified":216,
        "healthBase":0,
        "magickaModified":92,
        "magickaBase":92,
        "fatigueCurrent":216
      },
      "equipment":{
        "0":{
          "refId":"netch_leather_helm",
          "count":1,
          "charge":-1,
          "enchantmentCharge":-1
        },
        "1":{
          "refId":"netch_leather_boiled_cuirass",
          "count":1,
          "charge":-1,
          "enchantmentCharge":-1
        },
        "2":{
          "refId":"fur_greaves",
          "count":1,
          "charge":-1,
          "enchantmentCharge":-1
        },
        "4":{
          "refId":"chitin pauldron - right",
          "count":1,
          "charge":-1,
          "enchantmentCharge":-1
        },
        "5":{
          "refId":"netch_leather_gauntlet_left",
          "count":1,
          "charge":-1,
          "enchantmentCharge":-1
        },
        "7":{
          "refId":"netch_leather_boots",
          "count":1,
          "charge":-1,
          "enchantmentCharge":-1
        },
        "16":{
          "refId":"wooden staff",
          "count":1,
          "charge":-1,
          "enchantmentCharge":-1
        },
        "17":{
          "refId":"netch_leather_shield",
          "count":1,
          "charge":-1,
          "enchantmentCharge":-1
        }
      },
      "inventory":[{
          "refId":"netch_leather_boots",
          "count":1,
          "charge":-1,
          "enchantmentCharge":-1,
          "soul":""
        },{
          "refId":"fur_bracer_left",
          "count":1,
          "charge":-1,
          "enchantmentCharge":-1,
          "soul":""
        },{
          "refId":"netch_leather_boiled_cuirass",
          "count":1,
          "charge":-1,
          "enchantmentCharge":-1,
          "soul":""
        },{
          "refId":"netch_leather_gauntlet_left",
          "count":1,
          "charge":-1,
          "enchantmentCharge":-1,
          "soul":""
        },{
          "refId":"fur_greaves",
          "count":1,
          "charge":-1,
          "enchantmentCharge":-1,
          "soul":""
        },{
          "refId":"netch_leather_helm",
          "count":1,
          "charge":-1,
          "enchantmentCharge":-1,
          "soul":""
        },{
          "refId":"chitin pauldron - right",
          "count":1,
          "charge":-1,
          "enchantmentCharge":-1,
          "soul":""
        },{
          "refId":"netch_leather_shield",
          "count":1,
          "charge":-1,
          "enchantmentCharge":-1,
          "soul":""
        },{
          "refId":"pick_apprentice_01",
          "count":1,
          "charge":-1,
          "enchantmentCharge":-1,
          "soul":""
        },{
          "refId":"probe_apprentice_01",
          "count":1,
          "charge":-1,
          "enchantmentCharge":-1,
          "soul":""
        },{
          "refId":"wooden staff",
          "count":1,
          "charge":-1,
          "enchantmentCharge":-1,
          "soul":""
        }]
    },
    "56083-0":{
      "refId":"egg_kwama00",
      "inventory":[{
          "refId":"food_kwama_egg_02",
          "count":1,
          "charge":-1,
          "enchantmentCharge":-1,
          "soul":""
        }]
    },
    "56107-0":{
      "refId":"egg_kwama00",
      "inventory":[{
          "refId":"food_kwama_egg_02",
          "count":1,
          "charge":-1,
          "enchantmentCharge":-1,
          "soul":""
        }]
    },
    "55950-0":{
      "refId":"egg_kwama00",
      "inventory":[{
          "refId":"food_kwama_egg_02",
          "count":1,
          "charge":-1,
          "enchantmentCharge":-1,
          "soul":""
        }]
    },
    "56106-0":{
      "refId":"egg_kwama00",
      "inventory":[{
          "refId":"food_kwama_egg_02",
          "count":1,
          "charge":-1,
          "enchantmentCharge":-1,
          "soul":""
        }]
    },
    "56086-0":{
      "refId":"egg_kwama00",
      "inventory":[{
          "refId":"food_kwama_egg_02",
          "count":1,
          "charge":-1,
          "enchantmentCharge":-1,
          "soul":""
        }]
    },
    "56023-0":{
      "refId":"egg_kwama00",
      "inventory":[{
          "refId":"food_kwama_egg_02",
          "count":1,
          "charge":-1,
          "enchantmentCharge":-1,
          "soul":""
        }]
    },
    "56105-0":{
      "refId":"egg_kwama00",
      "inventory":[{
          "refId":"food_kwama_egg_02",
          "count":1,
          "charge":-1,
          "enchantmentCharge":-1,
          "soul":""
        }]
    },
    "56095-0":{
      "refId":"egg_kwama00",
      "inventory":[{
          "refId":"food_kwama_egg_02",
          "count":1,
          "charge":-1,
          "enchantmentCharge":-1,
          "soul":""
        }]
    },
    "56094-0":{
      "refId":"egg_kwama00",
      "inventory":[{
          "refId":"food_kwama_egg_02",
          "count":1,
          "charge":-1,
          "enchantmentCharge":-1,
          "soul":""
        }]
    },
    "56019-0":{
      "refId":"egg_kwama00",
      "inventory":[{
          "refId":"food_kwama_egg_02",
          "count":1,
          "charge":-1,
          "enchantmentCharge":-1,
          "soul":""
        }]
    },
    "56031-0":{
      "refId":"egg_kwama00",
      "inventory":[{
          "refId":"food_kwama_egg_02",
          "count":1,
          "charge":-1,
          "enchantmentCharge":-1,
          "soul":""
        }]
    },
    "56026-0":{
      "refId":"egg_kwama00",
      "inventory":[{
          "refId":"food_kwama_egg_02",
          "count":1,
          "charge":-1,
          "enchantmentCharge":-1,
          "soul":""
        }]
    },
    "56022-0":{
      "refId":"egg_kwama00",
      "inventory":[{
          "refId":"food_kwama_egg_02",
          "count":1,
          "charge":-1,
          "enchantmentCharge":-1,
          "soul":""
        }]
    },
    "55953-0":{
      "refId":"egg_kwama00",
      "inventory":[{
          "refId":"food_kwama_egg_02",
          "count":1,
          "charge":-1,
          "enchantmentCharge":-1,
          "soul":""
        }]
    },
    "56108-0":{
      "refId":"egg_kwama00",
      "inventory":[{
          "refId":"food_kwama_egg_02",
          "count":1,
          "charge":-1,
          "enchantmentCharge":-1,
          "soul":""
        }]
    },
    "56034-0":{
      "refId":"egg_kwama00",
      "inventory":[{
          "refId":"food_kwama_egg_02",
          "count":1,
          "charge":-1,
          "enchantmentCharge":-1,
          "soul":""
        }]
    }
  }
}