{
  "packets":{
    "actorList":[],
    "ai":[],
    "cellChangeFrom":[],
    "cellChangeTo":[],
    "container":["404136-0","404137-0","135324-0","135323-0"],
    "death":[],
    "delete":[],
    "doorState":[],
    "equipment":[],
    "lock":[],
    "place":[],
    "position":[],
    "scale":[],
    "spawn":[],
    "state":[],
    "statsDynamic":[],
    "trap":[]
  },
  "entry":{
    "creationTime":1547248249,
    "description":"Shashpilamat, Shrine"
  },
  "lastVisit":{
    "urm":1547248250
  },
  "recordLinks":[],
  "objectData":{
    "135323-0":{
      "refId":"durzol gro-dumulg",
      "inventory":[{
          "refId":"expensive_robe_03",
          "count":1,
          "charge":-1,
          "enchantmentCharge":-1,
          "soul":""
        },{
          "refId":"expensive_shoes_01",
          "count":1,
          "charge":-1,
          "enchantmentCharge":-1,
          "soul":""
        },{
          "refId":"common_ring_01",
          "count":1,
          "charge":-1,
          "enchantmentCharge":-1,
          "soul":""
        },{
          "refId":"common_amulet_01",
          "count":1,
          "charge":-1,
          "enchantmentCharge":-1,
          "soul":""
        },{
          "refId":"chitin shortsword",
          "count":1,
          "charge":-1,
          "enchantmentCharge":-1,
          "soul":""
        }]
    },
    "404137-0":{
      "refId":"com_chest_11_vault",
      "inventory":[{
          "refId":"exquisite_ring_02",
          "count":2,
          "charge":-1,
          "enchantmentCharge":-1,
          "soul":""
        },{
          "refId":"ingred_pearl_01",
          "count":1,
          "charge":-1,
          "enchantmentCharge":-1,
          "soul":""
        },{
          "refId":"ingred_ruby_01",
          "count":1,
          "charge":-1,
          "enchantmentCharge":-1,
          "soul":""
        },{
          "refId":"ingred_emerald_01",
          "count":1,
          "charge":-1,
          "enchantmentCharge":-1,
          "soul":""
        },{
          "refId":"gold_001",
          "count":297,
          "charge":-1,
          "enchantmentCharge":-1,
          "soul":""
        }]
    },
    "135324-0":{
      "refId":"yazgash gra-boga",
      "inventory":[{
          "refId":"orcish_bracer_right",
          "count":1,
          "charge":-1,
          "enchantmentCharge":-1,
          "soul":""
        },{
          "refId":"orcish_bracer_left",
          "count":1,
          "charge":-1,
          "enchantmentCharge":-1,
          "soul":""
        },{
          "refId":"orcish_boots",
          "count":1,
          "charge":-1,
          "enchantmentCharge":-1,
          "soul":""
        },{
          "refId":"orcish_greaves",
          "count":1,
          "charge":-1,
          "enchantmentCharge":-1,
          "soul":""
        },{
          "refId":"orcish_pauldron_right",
          "count":1,
          "charge":-1,
          "enchantmentCharge":-1,
          "soul":""
        },{
          "refId":"orcish_pauldron_left",
          "count":1,
          "charge":-1,
          "enchantmentCharge":-1,
          "soul":""
        },{
          "refId":"orcish_cuirass",
          "count":1,
          "charge":-1,
          "enchantmentCharge":-1,
          "soul":""
        },{
          "refId":"orcish_helm",
          "count":1,
          "charge":-1,
          "enchantmentCharge":-1,
          "soul":""
        },{
          "refId":"iron broadsword",
          "count":1,
          "charge":-1,
          "enchantmentCharge":-1,
          "soul":""
        }]
    },
    "404136-0":{
      "refId":"com_chest_02_lev_gold",
      "inventory":[{
          "refId":"gold_001",
          "count":74,
          "charge":-1,
          "enchantmentCharge":-1,
          "soul":""
        }]
    }
  }
}