{
  "packets":{
    "actorList":["258292-0","258293-0","258294-0","258295-0","258296-0","268852-0","268853-0","480873-0","480874-0","480875-0","480876-0"],
    "ai":[],
    "cellChangeFrom":[],
    "cellChangeTo":[],
    "container":["258299-0","258313-0","281998-0","281999-0","334323-0","334324-0","334340-0","422615-0","422616-0","422620-0","422650-0","258292-0","258293-0","258294-0","258295-0","258296-0","268852-0","268853-0","480873-0","480874-0","480875-0","480876-0"],
    "death":[],
    "delete":[],
    "doorState":[],
    "equipment":["258292-0","258293-0","258294-0","258295-0","258296-0","268852-0","268853-0","480873-0","480874-0","480875-0","480876-0"],
    "lock":[],
    "place":[],
    "position":["258292-0","258293-0","258294-0","258295-0","258296-0","268852-0","268853-0","480873-0","480874-0","480875-0","480876-0"],
    "scale":[],
    "spawn":[],
    "state":[],
    "statsDynamic":["258292-0","258293-0","258294-0","258295-0","258296-0","268852-0","268853-0","480873-0","480874-0","480875-0","480876-0"],
    "trap":[]
  },
  "entry":{
    "creationTime":1547248262,
    "description":"Sudanit Mine"
  },
  "lastVisit":{
    "urm":1547248263
  },
  "recordLinks":[],
  "objectData":{
    "281999-0":{
      "refId":"rock_ebony_07",
      "inventory":[{
          "refId":"ingred_raw_ebony_01",
          "count":4,
          "charge":-1,
          "enchantmentCharge":-1,
          "soul":""
        }]
    },
    "258295-0":{
      "refId":"bralyn androthi",
      "location":{
        "posX":-363.95153808594,
        "posZ":-1649.8676757813,
        "posY":1570.7430419922,
        "rotX":0,
        "rotY":0,
        "rotZ":5.5495553016663
      },
      "stats":{
        "healthCurrent":82,
        "magickaCurrent":86,
        "healthModified":82,
        "fatigueBase":201,
        "fatigueModified":201,
        "healthBase":82,
        "magickaModified":86,
        "magickaBase":86,
        "fatigueCurrent":201
      },
      "equipment":{
        "7":{
          "refId":"common_shoes_02",
          "count":1,
          "charge":-1,
          "enchantmentCharge":-1
        },
        "8":{
          "refId":"common_shirt_02_h",
          "count":1,
          "charge":-1,
          "enchantmentCharge":-1
        },
        "16":{
          "refId":"miner's pick",
          "count":1,
          "charge":-1,
          "enchantmentCharge":-1
        },
        "9":{
          "refId":"common_pants_03",
          "count":1,
          "charge":-1,
          "enchantmentCharge":-1
        }
      },
      "inventory":[{
          "refId":"common_shirt_02_h",
          "count":1,
          "charge":-1,
          "enchantmentCharge":-1,
          "soul":""
        },{
          "refId":"common_shoes_02",
          "count":1,
          "charge":-1,
          "enchantmentCharge":-1,
          "soul":""
        },{
          "refId":"common_pants_03",
          "count":1,
          "charge":-1,
          "enchantmentCharge":-1,
          "soul":""
        },{
          "refId":"ingred_raw_ebony_01",
          "count":1,
          "charge":-1,
          "enchantmentCharge":-1,
          "soul":""
        },{
          "refId":"miner's pick",
          "count":1,
          "charge":-1,
          "enchantmentCharge":-1,
          "soul":""
        }]
    },
    "258293-0":{
      "refId":"danel indaren",
      "location":{
        "posX":-1346.498046875,
        "posZ":-1672.275390625,
        "posY":3776.6391601563,
        "rotX":0,
        "rotY":0,
        "rotZ":3.1331844329834
      },
      "stats":{
        "healthCurrent":75,
        "magickaCurrent":100,
        "healthModified":75,
        "fatigueBase":216,
        "fatigueModified":216,
        "healthBase":75,
        "magickaModified":100,
        "magickaBase":100,
        "fatigueCurrent":216
      },
      "equipment":{
        "7":{
          "refId":"common_shoes_04",
          "count":1,
          "charge":-1,
          "enchantmentCharge":-1
        },
        "11":{
          "refId":"common_robe_01",
          "count":1,
          "charge":-1,
          "enchantmentCharge":-1
        }
      },
      "inventory":[{
          "refId":"p_drain_strength_q",
          "count":1,
          "charge":-1,
          "enchantmentCharge":-1,
          "soul":""
        },{
          "refId":"common_robe_01",
          "count":1,
          "charge":-1,
          "enchantmentCharge":-1,
          "soul":""
        },{
          "refId":"common_shoes_04",
          "count":1,
          "charge":-1,
          "enchantmentCharge":-1,
          "soul":""
        }]
    },
    "422620-0":{
      "refId":"crate_01_ebony",
      "inventory":[{
          "refId":"ingred_raw_ebony_01",
          "count":4,
          "charge":-1,
          "enchantmentCharge":-1,
          "soul":""
        }]
    },
    "334340-0":{
      "refId":"rock_ebony_04",
      "inventory":[{
          "refId":"ingred_raw_ebony_01",
          "count":4,
          "charge":-1,
          "enchantmentCharge":-1,
          "soul":""
        }]
    },
    "258294-0":{
      "refId":"belvis sedri",
      "location":{
        "posX":-1414.9581298828,
        "posZ":-1653.2863769531,
        "posY":2071.9821777344,
        "rotX":0,
        "rotY":0,
        "rotZ":2.0000007152557
      },
      "stats":{
        "healthCurrent":122,
        "magickaCurrent":94,
        "healthModified":122,
        "fatigueBase":239,
        "fatigueModified":239,
        "healthBase":122,
        "magickaModified":94,
        "magickaBase":94,
        "fatigueCurrent":239
      },
      "equipment":{
        "7":{
          "refId":"common_shoes_03",
          "count":1,
          "charge":-1,
          "enchantmentCharge":-1
        },
        "8":{
          "refId":"common_shirt_01",
          "count":1,
          "charge":-1,
          "enchantmentCharge":-1
        },
        "16":{
          "refId":"miner's pick",
          "count":1,
          "charge":-1,
          "enchantmentCharge":-1
        },
        "9":{
          "refId":"common_pants_05",
          "count":1,
          "charge":-1,
          "enchantmentCharge":-1
        }
      },
      "inventory":[{
          "refId":"common_shirt_01",
          "count":1,
          "charge":-1,
          "enchantmentCharge":-1,
          "soul":""
        },{
          "refId":"common_shoes_03",
          "count":1,
          "charge":-1,
          "enchantmentCharge":-1,
          "soul":""
        },{
          "refId":"common_pants_05",
          "count":1,
          "charge":-1,
          "enchantmentCharge":-1,
          "soul":""
        },{
          "refId":"miner's pick",
          "count":1,
          "charge":-1,
          "enchantmentCharge":-1,
          "soul":""
        }]
    },
    "258292-0":{
      "refId":"darns tedalen",
      "location":{
        "posX":-1354.7030029297,
        "posZ":-1729.6779785156,
        "posY":3465.2915039063,
        "rotX":0,
        "rotY":0,
        "rotZ":2.0938053131104
      },
      "stats":{
        "healthCurrent":147,
        "magickaCurrent":110,
        "healthModified":147,
        "fatigueBase":284,
        "fatigueModified":284,
        "healthBase":147,
        "magickaModified":110,
        "magickaBase":110,
        "fatigueCurrent":284
      },
      "equipment":{
        "1":{
          "refId":"trollbone_cuirass",
          "count":1,
          "charge":-1,
          "enchantmentCharge":-1
        },
        "7":{
          "refId":"netch_leather_boots",
          "count":1,
          "charge":-1,
          "enchantmentCharge":-1
        },
        "8":{
          "refId":"common_shirt_04",
          "count":1,
          "charge":-1,
          "enchantmentCharge":-1
        },
        "16":{
          "refId":"iron saber",
          "count":1,
          "charge":-1,
          "enchantmentCharge":-1
        },
        "9":{
          "refId":"common_pants_02",
          "count":1,
          "charge":-1,
          "enchantmentCharge":-1
        }
      },
      "inventory":[{
          "refId":"netch_leather_boots",
          "count":1,
          "charge":-1,
          "enchantmentCharge":-1,
          "soul":""
        },{
          "refId":"trollbone_cuirass",
          "count":1,
          "charge":-1,
          "enchantmentCharge":-1,
          "soul":""
        },{
          "refId":"common_shirt_04",
          "count":1,
          "charge":-1,
          "enchantmentCharge":-1,
          "soul":""
        },{
          "refId":"common_pants_02",
          "count":1,
          "charge":-1,
          "enchantmentCharge":-1,
          "soul":""
        },{
          "refId":"iron saber",
          "count":1,
          "charge":-1,
          "enchantmentCharge":-1,
          "soul":""
        }]
    },
    "422615-0":{
      "refId":"barrel_01_cheapfood5",
      "inventory":[{
          "refId":"food_kwama_egg_02",
          "count":5,
          "charge":-1,
          "enchantmentCharge":-1,
          "soul":""
        }]
    },
    "258299-0":{
      "refId":"rock_ebony_05",
      "inventory":[{
          "refId":"ingred_raw_ebony_01",
          "count":4,
          "charge":-1,
          "enchantmentCharge":-1,
          "soul":""
        }]
    },
    "268852-0":{
      "refId":"golana giralvel",
      "location":{
        "posX":1252.8336181641,
        "posZ":-1277.6826171875,
        "posY":1063.3479003906,
        "rotX":0,
        "rotY":0,
        "rotZ":3.9269907474518
      },
      "stats":{
        "healthCurrent":98,
        "magickaCurrent":94,
        "healthModified":98,
        "fatigueBase":229,
        "fatigueModified":229,
        "healthBase":98,
        "magickaModified":94,
        "magickaBase":94,
        "fatigueCurrent":229
      },
      "equipment":{
        "1":{
          "refId":"newtscale_cuirass",
          "count":1,
          "charge":-1,
          "enchantmentCharge":-1
        },
        "7":{
          "refId":"common_shoes_01",
          "count":1,
          "charge":-1,
          "enchantmentCharge":-1
        },
        "8":{
          "refId":"common_shirt_02",
          "count":1,
          "charge":-1,
          "enchantmentCharge":-1
        },
        "16":{
          "refId":"iron longsword",
          "count":1,
          "charge":-1,
          "enchantmentCharge":-1
        },
        "9":{
          "refId":"common_pants_04",
          "count":1,
          "charge":-1,
          "enchantmentCharge":-1
        }
      },
      "inventory":[{
          "refId":"newtscale_cuirass",
          "count":1,
          "charge":-1,
          "enchantmentCharge":-1,
          "soul":""
        },{
          "refId":"common_shirt_02",
          "count":1,
          "charge":-1,
          "enchantmentCharge":-1,
          "soul":""
        },{
          "refId":"common_shoes_01",
          "count":1,
          "charge":-1,
          "enchantmentCharge":-1,
          "soul":""
        },{
          "refId":"common_pants_04",
          "count":1,
          "charge":-1,
          "enchantmentCharge":-1,
          "soul":""
        },{
          "refId":"iron arrow",
          "count":50,
          "charge":-1,
          "enchantmentCharge":-1,
          "soul":""
        },{
          "refId":"short bow",
          "count":1,
          "charge":-1,
          "enchantmentCharge":-1,
          "soul":""
        },{
          "refId":"iron longsword",
          "count":1,
          "charge":-1,
          "enchantmentCharge":-1,
          "soul":""
        }]
    },
    "258313-0":{
      "refId":"rock_ebony_07",
      "inventory":[{
          "refId":"ingred_raw_ebony_01",
          "count":5,
          "charge":-1,
          "enchantmentCharge":-1,
          "soul":""
        }]
    },
    "258296-0":{
      "refId":"galeri uveleth",
      "location":{
        "posX":-432.09252929688,
        "posZ":-1654.5854492188,
        "posY":2317.0759277344,
        "rotX":0,
        "rotY":0,
        "rotZ":0.68318474292755
      },
      "stats":{
        "healthCurrent":77,
        "magickaCurrent":86,
        "healthModified":77,
        "fatigueBase":191,
        "fatigueModified":191,
        "healthBase":77,
        "magickaModified":86,
        "magickaBase":86,
        "fatigueCurrent":191
      },
      "equipment":{
        "7":{
          "refId":"common_shoes_05",
          "count":1,
          "charge":-1,
          "enchantmentCharge":-1
        },
        "8":{
          "refId":"common_shirt_01",
          "count":1,
          "charge":-1,
          "enchantmentCharge":-1
        },
        "16":{
          "refId":"miner's pick",
          "count":1,
          "charge":-1,
          "enchantmentCharge":-1
        },
        "9":{
          "refId":"common_pants_02",
          "count":1,
          "charge":-1,
          "enchantmentCharge":-1
        }
      },
      "inventory":[{
          "refId":"common_shirt_01",
          "count":1,
          "charge":-1,
          "enchantmentCharge":-1,
          "soul":""
        },{
          "refId":"common_shoes_05",
          "count":1,
          "charge":-1,
          "enchantmentCharge":-1,
          "soul":""
        },{
          "refId":"common_pants_02",
          "count":1,
          "charge":-1,
          "enchantmentCharge":-1,
          "soul":""
        },{
          "refId":"ingred_raw_ebony_01",
          "count":1,
          "charge":-1,
          "enchantmentCharge":-1,
          "soul":""
        },{
          "refId":"miner's pick",
          "count":1,
          "charge":-1,
          "enchantmentCharge":-1,
          "soul":""
        }]
    },
    "480873-0":{
      "refId":"redoran guard male",
      "location":{
        "posX":1303.400390625,
        "posZ":-514.47875976563,
        "posY":2585.4040527344,
        "rotX":0,
        "rotY":0,
        "rotZ":0
      },
      "stats":{
        "healthCurrent":210,
        "magickaCurrent":122,
        "healthModified":210,
        "fatigueBase":307,
        "fatigueModified":307,
        "healthBase":210,
        "magickaModified":122,
        "magickaBase":122,
        "fatigueCurrent":307
      },
      "equipment":{
        "0":{
          "refId":"bonemold_gah-julan_helm",
          "count":1,
          "charge":-1,
          "enchantmentCharge":-1
        },
        "1":{
          "refId":"bonemold_gah-julan_cuirass",
          "count":1,
          "charge":-1,
          "enchantmentCharge":-1
        },
        "2":{
          "refId":"bonemold_greaves",
          "count":1,
          "charge":-1,
          "enchantmentCharge":-1
        },
        "3":{
          "refId":"bonemold_gah-julan_pauldron_l",
          "count":1,
          "charge":-1,
          "enchantmentCharge":-1
        },
        "4":{
          "refId":"bonemold_gah-julan_pauldron_r",
          "count":1,
          "charge":-1,
          "enchantmentCharge":-1
        },
        "5":{
          "refId":"bonemold_bracer_left",
          "count":1,
          "charge":-1,
          "enchantmentCharge":-1
        },
        "6":{
          "refId":"bonemold_bracer_right",
          "count":1,
          "charge":-1,
          "enchantmentCharge":-1
        },
        "7":{
          "refId":"bonemold_boots",
          "count":1,
          "charge":-1,
          "enchantmentCharge":-1
        },
        "8":{
          "refId":"extravagant_shirt_01",
          "count":1,
          "charge":-1,
          "enchantmentCharge":-1
        },
        "9":{
          "refId":"extravagant_pants_01",
          "count":1,
          "charge":-1,
          "enchantmentCharge":-1
        },
        "14":{
          "refId":"expensive_amulet_01",
          "count":1,
          "charge":-1,
          "enchantmentCharge":-1
        },
        "16":{
          "refId":"steel mace",
          "count":1,
          "charge":-1,
          "enchantmentCharge":-1
        }
      },
      "inventory":[{
          "refId":"bonemold_bracer_right",
          "count":1,
          "charge":-1,
          "enchantmentCharge":-1,
          "soul":""
        },{
          "refId":"bonemold_bracer_left",
          "count":1,
          "charge":-1,
          "enchantmentCharge":-1,
          "soul":""
        },{
          "refId":"bonemold_boots",
          "count":1,
          "charge":-1,
          "enchantmentCharge":-1,
          "soul":""
        },{
          "refId":"bonemold_greaves",
          "count":1,
          "charge":-1,
          "enchantmentCharge":-1,
          "soul":""
        },{
          "refId":"bonemold_gah-julan_pauldron_r",
          "count":1,
          "charge":-1,
          "enchantmentCharge":-1,
          "soul":""
        },{
          "refId":"bonemold_gah-julan_pauldron_l",
          "count":1,
          "charge":-1,
          "enchantmentCharge":-1,
          "soul":""
        },{
          "refId":"bonemold_gah-julan_cuirass",
          "count":1,
          "charge":-1,
          "enchantmentCharge":-1,
          "soul":""
        },{
          "refId":"bonemold_gah-julan_helm",
          "count":1,
          "charge":-1,
          "enchantmentCharge":-1,
          "soul":""
        },{
          "refId":"expensive_amulet_01",
          "count":1,
          "charge":-1,
          "enchantmentCharge":-1,
          "soul":""
        },{
          "refId":"extravagant_glove_left_01",
          "count":1,
          "charge":-1,
          "enchantmentCharge":-1,
          "soul":""
        },{
          "refId":"extravagant_glove_right_01",
          "count":1,
          "charge":-1,
          "enchantmentCharge":-1,
          "soul":""
        },{
          "refId":"extravagant_shirt_01",
          "count":1,
          "charge":-1,
          "enchantmentCharge":-1,
          "soul":""
        },{
          "refId":"extravagant_shoes_01",
          "count":1,
          "charge":-1,
          "enchantmentCharge":-1,
          "soul":""
        },{
          "refId":"extravagant_pants_01",
          "count":1,
          "charge":-1,
          "enchantmentCharge":-1,
          "soul":""
        },{
          "refId":"torch_infinite_time",
          "count":1,
          "charge":-1,
          "enchantmentCharge":-1,
          "soul":""
        },{
          "refId":"steel mace",
          "count":1,
          "charge":-1,
          "enchantmentCharge":-1,
          "soul":""
        }]
    },
    "480875-0":{
      "refId":"redoran guard male",
      "location":{
        "posX":1545.2014160156,
        "posZ":-1277.8118896484,
        "posY":618.21099853516,
        "rotX":0,
        "rotY":0,
        "rotZ":0
      },
      "stats":{
        "healthCurrent":210,
        "magickaCurrent":122,
        "healthModified":210,
        "fatigueBase":307,
        "fatigueModified":307,
        "healthBase":210,
        "magickaModified":122,
        "magickaBase":122,
        "fatigueCurrent":307
      },
      "equipment":{
        "0":{
          "refId":"bonemold_gah-julan_helm",
          "count":1,
          "charge":-1,
          "enchantmentCharge":-1
        },
        "1":{
          "refId":"bonemold_gah-julan_cuirass",
          "count":1,
          "charge":-1,
          "enchantmentCharge":-1
        },
        "2":{
          "refId":"bonemold_greaves",
          "count":1,
          "charge":-1,
          "enchantmentCharge":-1
        },
        "3":{
          "refId":"bonemold_gah-julan_pauldron_l",
          "count":1,
          "charge":-1,
          "enchantmentCharge":-1
        },
        "4":{
          "refId":"bonemold_gah-julan_pauldron_r",
          "count":1,
          "charge":-1,
          "enchantmentCharge":-1
        },
        "5":{
          "refId":"bonemold_bracer_left",
          "count":1,
          "charge":-1,
          "enchantmentCharge":-1
        },
        "6":{
          "refId":"bonemold_bracer_right",
          "count":1,
          "charge":-1,
          "enchantmentCharge":-1
        },
        "7":{
          "refId":"bonemold_boots",
          "count":1,
          "charge":-1,
          "enchantmentCharge":-1
        },
        "8":{
          "refId":"extravagant_shirt_01",
          "count":1,
          "charge":-1,
          "enchantmentCharge":-1
        },
        "9":{
          "refId":"extravagant_pants_01",
          "count":1,
          "charge":-1,
          "enchantmentCharge":-1
        },
        "14":{
          "refId":"expensive_amulet_01",
          "count":1,
          "charge":-1,
          "enchantmentCharge":-1
        },
        "16":{
          "refId":"steel mace",
          "count":1,
          "charge":-1,
          "enchantmentCharge":-1
        }
      },
      "inventory":[{
          "refId":"bonemold_bracer_right",
          "count":1,
          "charge":-1,
          "enchantmentCharge":-1,
          "soul":""
        },{
          "refId":"bonemold_bracer_left",
          "count":1,
          "charge":-1,
          "enchantmentCharge":-1,
          "soul":""
        },{
          "refId":"bonemold_boots",
          "count":1,
          "charge":-1,
          "enchantmentCharge":-1,
          "soul":""
        },{
          "refId":"bonemold_greaves",
          "count":1,
          "charge":-1,
          "enchantmentCharge":-1,
          "soul":""
        },{
          "refId":"bonemold_gah-julan_pauldron_r",
          "count":1,
          "charge":-1,
          "enchantmentCharge":-1,
          "soul":""
        },{
          "refId":"bonemold_gah-julan_pauldron_l",
          "count":1,
          "charge":-1,
          "enchantmentCharge":-1,
          "soul":""
        },{
          "refId":"bonemold_gah-julan_cuirass",
          "count":1,
          "charge":-1,
          "enchantmentCharge":-1,
          "soul":""
        },{
          "refId":"bonemold_gah-julan_helm",
          "count":1,
          "charge":-1,
          "enchantmentCharge":-1,
          "soul":""
        },{
          "refId":"expensive_amulet_01",
          "count":1,
          "charge":-1,
          "enchantmentCharge":-1,
          "soul":""
        },{
          "refId":"extravagant_glove_left_01",
          "count":1,
          "charge":-1,
          "enchantmentCharge":-1,
          "soul":""
        },{
          "refId":"extravagant_glove_right_01",
          "count":1,
          "charge":-1,
          "enchantmentCharge":-1,
          "soul":""
        },{
          "refId":"extravagant_shirt_01",
          "count":1,
          "charge":-1,
          "enchantmentCharge":-1,
          "soul":""
        },{
          "refId":"extravagant_shoes_01",
          "count":1,
          "charge":-1,
          "enchantmentCharge":-1,
          "soul":""
        },{
          "refId":"extravagant_pants_01",
          "count":1,
          "charge":-1,
          "enchantmentCharge":-1,
          "soul":""
        },{
          "refId":"torch_infinite_time",
          "count":1,
          "charge":-1,
          "enchantmentCharge":-1,
          "soul":""
        },{
          "refId":"steel mace",
          "count":1,
          "charge":-1,
          "enchantmentCharge":-1,
          "soul":""
        }]
    },
    "422650-0":{
      "refId":"com_chest_11_clothing",
      "inventory":[{
          "refId":"common_belt_02",
          "count":1,
          "charge":-1,
          "enchantmentCharge":-1,
          "soul":""
        },{
          "refId":"common_shirt_02",
          "count":1,
          "charge":-1,
          "enchantmentCharge":-1,
          "soul":""
        },{
          "refId":"common_shoes_02",
          "count":1,
          "charge":-1,
          "enchantmentCharge":-1,
          "soul":""
        },{
          "refId":"common_pants_01",
          "count":1,
          "charge":-1,
          "enchantmentCharge":-1,
          "soul":""
        },{
          "refId":"gold_001",
          "count":3,
          "charge":-1,
          "enchantmentCharge":-1,
          "soul":""
        }]
    },
    "480874-0":{
      "refId":"redoran guard male",
      "location":{
        "posX":-752.27703857422,
        "posZ":-1660.5556640625,
        "posY":1452.3785400391,
        "rotX":0,
        "rotY":0,
        "rotZ":0
      },
      "stats":{
        "healthCurrent":210,
        "magickaCurrent":122,
        "healthModified":210,
        "fatigueBase":307,
        "fatigueModified":307,
        "healthBase":210,
        "magickaModified":122,
        "magickaBase":122,
        "fatigueCurrent":307
      },
      "equipment":{
        "0":{
          "refId":"bonemold_gah-julan_helm",
          "count":1,
          "charge":-1,
          "enchantmentCharge":-1
        },
        "1":{
          "refId":"bonemold_gah-julan_cuirass",
          "count":1,
          "charge":-1,
          "enchantmentCharge":-1
        },
        "2":{
          "refId":"bonemold_greaves",
          "count":1,
          "charge":-1,
          "enchantmentCharge":-1
        },
        "3":{
          "refId":"bonemold_gah-julan_pauldron_l",
          "count":1,
          "charge":-1,
          "enchantmentCharge":-1
        },
        "4":{
          "refId":"bonemold_gah-julan_pauldron_r",
          "count":1,
          "charge":-1,
          "enchantmentCharge":-1
        },
        "5":{
          "refId":"bonemold_bracer_left",
          "count":1,
          "charge":-1,
          "enchantmentCharge":-1
        },
        "6":{
          "refId":"bonemold_bracer_right",
          "count":1,
          "charge":-1,
          "enchantmentCharge":-1
        },
        "7":{
          "refId":"bonemold_boots",
          "count":1,
          "charge":-1,
          "enchantmentCharge":-1
        },
        "8":{
          "refId":"extravagant_shirt_01",
          "count":1,
          "charge":-1,
          "enchantmentCharge":-1
        },
        "9":{
          "refId":"extravagant_pants_01",
          "count":1,
          "charge":-1,
          "enchantmentCharge":-1
        },
        "14":{
          "refId":"expensive_amulet_01",
          "count":1,
          "charge":-1,
          "enchantmentCharge":-1
        },
        "16":{
          "refId":"steel mace",
          "count":1,
          "charge":-1,
          "enchantmentCharge":-1
        }
      },
      "inventory":[{
          "refId":"bonemold_bracer_right",
          "count":1,
          "charge":-1,
          "enchantmentCharge":-1,
          "soul":""
        },{
          "refId":"bonemold_bracer_left",
          "count":1,
          "charge":-1,
          "enchantmentCharge":-1,
          "soul":""
        },{
          "refId":"bonemold_boots",
          "count":1,
          "charge":-1,
          "enchantmentCharge":-1,
          "soul":""
        },{
          "refId":"bonemold_greaves",
          "count":1,
          "charge":-1,
          "enchantmentCharge":-1,
          "soul":""
        },{
          "refId":"bonemold_gah-julan_pauldron_r",
          "count":1,
          "charge":-1,
          "enchantmentCharge":-1,
          "soul":""
        },{
          "refId":"bonemold_gah-julan_pauldron_l",
          "count":1,
          "charge":-1,
          "enchantmentCharge":-1,
          "soul":""
        },{
          "refId":"bonemold_gah-julan_cuirass",
          "count":1,
          "charge":-1,
          "enchantmentCharge":-1,
          "soul":""
        },{
          "refId":"bonemold_gah-julan_helm",
          "count":1,
          "charge":-1,
          "enchantmentCharge":-1,
          "soul":""
        },{
          "refId":"expensive_amulet_01",
          "count":1,
          "charge":-1,
          "enchantmentCharge":-1,
          "soul":""
        },{
          "refId":"extravagant_glove_left_01",
          "count":1,
          "charge":-1,
          "enchantmentCharge":-1,
          "soul":""
        },{
          "refId":"extravagant_glove_right_01",
          "count":1,
          "charge":-1,
          "enchantmentCharge":-1,
          "soul":""
        },{
          "refId":"extravagant_shirt_01",
          "count":1,
          "charge":-1,
          "enchantmentCharge":-1,
          "soul":""
        },{
          "refId":"extravagant_shoes_01",
          "count":1,
          "charge":-1,
          "enchantmentCharge":-1,
          "soul":""
        },{
          "refId":"extravagant_pants_01",
          "count":1,
          "charge":-1,
          "enchantmentCharge":-1,
          "soul":""
        },{
          "refId":"torch_infinite_time",
          "count":1,
          "charge":-1,
          "enchantmentCharge":-1,
          "soul":""
        },{
          "refId":"steel mace",
          "count":1,
          "charge":-1,
          "enchantmentCharge":-1,
          "soul":""
        }]
    },
    "422616-0":{
      "refId":"barrel_01_drinks",
      "inventory":[{
          "refId":"potion_local_liquor_01",
          "count":2,
          "charge":-1,
          "enchantmentCharge":-1,
          "soul":""
        },{
          "refId":"potion_local_brew_01",
          "count":1,
          "charge":-1,
          "enchantmentCharge":-1,
          "soul":""
        },{
          "refId":"potion_comberry_wine_01",
          "count":2,
          "charge":-1,
          "enchantmentCharge":-1,
          "soul":""
        }]
    },
    "281998-0":{
      "refId":"rock_ebony_07",
      "inventory":[{
          "refId":"ingred_raw_ebony_01",
          "count":2,
          "charge":-1,
          "enchantmentCharge":-1,
          "soul":""
        }]
    },
    "334323-0":{
      "refId":"rock_ebony_05",
      "inventory":[{
          "refId":"ingred_raw_ebony_01",
          "count":5,
          "charge":-1,
          "enchantmentCharge":-1,
          "soul":""
        }]
    },
    "334324-0":{
      "refId":"rock_ebony_05",
      "inventory":[{
          "refId":"ingred_raw_ebony_01",
          "count":6,
          "charge":-1,
          "enchantmentCharge":-1,
          "soul":""
        }]
    },
    "268853-0":{
      "refId":"mils andrethi",
      "location":{
        "posX":1217.2716064453,
        "posZ":-512.35009765625,
        "posY":2344.9145507813,
        "rotX":0,
        "rotY":0,
        "rotZ":2.8500001430511
      },
      "stats":{
        "healthCurrent":122,
        "magickaCurrent":94,
        "healthModified":122,
        "fatigueBase":239,
        "fatigueModified":239,
        "healthBase":122,
        "magickaModified":94,
        "magickaBase":94,
        "fatigueCurrent":239
      },
      "equipment":{
        "7":{
          "refId":"common_shoes_04",
          "count":1,
          "charge":-1,
          "enchantmentCharge":-1
        },
        "8":{
          "refId":"common_shirt_03",
          "count":1,
          "charge":-1,
          "enchantmentCharge":-1
        },
        "16":{
          "refId":"miner's pick",
          "count":1,
          "charge":-1,
          "enchantmentCharge":-1
        },
        "9":{
          "refId":"common_pants_04",
          "count":1,
          "charge":-1,
          "enchantmentCharge":-1
        }
      },
      "inventory":[{
          "refId":"common_shirt_03",
          "count":1,
          "charge":-1,
          "enchantmentCharge":-1,
          "soul":""
        },{
          "refId":"common_shoes_04",
          "count":1,
          "charge":-1,
          "enchantmentCharge":-1,
          "soul":""
        },{
          "refId":"common_pants_04",
          "count":1,
          "charge":-1,
          "enchantmentCharge":-1,
          "soul":""
        },{
          "refId":"miner's pick",
          "count":1,
          "charge":-1,
          "enchantmentCharge":-1,
          "soul":""
        }]
    },
    "480876-0":{
      "refId":"redoran guard male",
      "location":{
        "posX":-1264.7794189453,
        "posZ":-1663.1674804688,
        "posY":2436.32421875,
        "rotX":0,
        "rotY":0,
        "rotZ":0
      },
      "stats":{
        "healthCurrent":210,
        "magickaCurrent":122,
        "healthModified":210,
        "fatigueBase":307,
        "fatigueModified":307,
        "healthBase":210,
        "magickaModified":122,
        "magickaBase":122,
        "fatigueCurrent":307
      },
      "equipment":{
        "0":{
          "refId":"bonemold_gah-julan_helm",
          "count":1,
          "charge":-1,
          "enchantmentCharge":-1
        },
        "1":{
          "refId":"bonemold_gah-julan_cuirass",
          "count":1,
          "charge":-1,
          "enchantmentCharge":-1
        },
        "2":{
          "refId":"bonemold_greaves",
          "count":1,
          "charge":-1,
          "enchantmentCharge":-1
        },
        "3":{
          "refId":"bonemold_gah-julan_pauldron_l",
          "count":1,
          "charge":-1,
          "enchantmentCharge":-1
        },
        "4":{
          "refId":"bonemold_gah-julan_pauldron_r",
          "count":1,
          "charge":-1,
          "enchantmentCharge":-1
        },
        "5":{
          "refId":"bonemold_bracer_left",
          "count":1,
          "charge":-1,
          "enchantmentCharge":-1
        },
        "6":{
          "refId":"bonemold_bracer_right",
          "count":1,
          "charge":-1,
          "enchantmentCharge":-1
        },
        "7":{
          "refId":"bonemold_boots",
          "count":1,
          "charge":-1,
          "enchantmentCharge":-1
        },
        "8":{
          "refId":"extravagant_shirt_01",
          "count":1,
          "charge":-1,
          "enchantmentCharge":-1
        },
        "9":{
          "refId":"extravagant_pants_01",
          "count":1,
          "charge":-1,
          "enchantmentCharge":-1
        },
        "14":{
          "refId":"expensive_amulet_01",
          "count":1,
          "charge":-1,
          "enchantmentCharge":-1
        },
        "16":{
          "refId":"steel mace",
          "count":1,
          "charge":-1,
          "enchantmentCharge":-1
        }
      },
      "inventory":[{
          "refId":"bonemold_bracer_right",
          "count":1,
          "charge":-1,
          "enchantmentCharge":-1,
          "soul":""
        },{
          "refId":"bonemold_bracer_left",
          "count":1,
          "charge":-1,
          "enchantmentCharge":-1,
          "soul":""
        },{
          "refId":"bonemold_boots",
          "count":1,
          "charge":-1,
          "enchantmentCharge":-1,
          "soul":""
        },{
          "refId":"bonemold_greaves",
          "count":1,
          "charge":-1,
          "enchantmentCharge":-1,
          "soul":""
        },{
          "refId":"bonemold_gah-julan_pauldron_r",
          "count":1,
          "charge":-1,
          "enchantmentCharge":-1,
          "soul":""
        },{
          "refId":"bonemold_gah-julan_pauldron_l",
          "count":1,
          "charge":-1,
          "enchantmentCharge":-1,
          "soul":""
        },{
          "refId":"bonemold_gah-julan_cuirass",
          "count":1,
          "charge":-1,
          "enchantmentCharge":-1,
          "soul":""
        },{
          "refId":"bonemold_gah-julan_helm",
          "count":1,
          "charge":-1,
          "enchantmentCharge":-1,
          "soul":""
        },{
          "refId":"expensive_amulet_01",
          "count":1,
          "charge":-1,
          "enchantmentCharge":-1,
          "soul":""
        },{
          "refId":"extravagant_glove_left_01",
          "count":1,
          "charge":-1,
          "enchantmentCharge":-1,
          "soul":""
        },{
          "refId":"extravagant_glove_right_01",
          "count":1,
          "charge":-1,
          "enchantmentCharge":-1,
          "soul":""
        },{
          "refId":"extravagant_shirt_01",
          "count":1,
          "charge":-1,
          "enchantmentCharge":-1,
          "soul":""
        },{
          "refId":"extravagant_shoes_01",
          "count":1,
          "charge":-1,
          "enchantmentCharge":-1,
          "soul":""
        },{
          "refId":"extravagant_pants_01",
          "count":1,
          "charge":-1,
          "enchantmentCharge":-1,
          "soul":""
        },{
          "refId":"torch_infinite_time",
          "count":1,
          "charge":-1,
          "enchantmentCharge":-1,
          "soul":""
        },{
          "refId":"steel mace",
          "count":1,
          "charge":-1,
          "enchantmentCharge":-1,
          "soul":""
        }]
    }
  }
}