{
  "packets":{
    "actorList":["0-1908"],
    "ai":[],
    "cellChangeFrom":[],
    "cellChangeTo":[],
    "container":[],
    "death":[],
    "delete":[],
    "doorState":[],
    "equipment":[],
    "lock":[],
    "place":[],
    "position":[],
    "scale":[],
    "spawn":["0-1908"],
    "state":[],
    "statsDynamic":[],
    "trap":[]
  },
  "entry":{
    "creationTime":1547248364,
    "description":"Vivec, Puzzle Canal, Level 2"
  },
  "lastVisit":{
    "urm":1547248365
  },
  "recordLinks":[],
  "objectData":{
    "0-1908":{
      "refId":"rat",
      "location":{
        "posX":2447,
        "posZ":160.00018310547,
        "posY":2063.9997558594,
        "rotX":0,
        "rotY":0,
        "rotZ":0
      }
    }
  }
}